sinapsis_data_writers/__init__.py
sinapsis_data_writers/helpers/__init__.py
sinapsis_data_writers/helpers/tags.py
sinapsis_data_writers/templates/__init__.py
sinapsis_data_writers/templates/annotation_writers/__init__.py
sinapsis_data_writers/templates/annotation_writers/base_annotation_writer.py
sinapsis_data_writers/templates/annotation_writers/coco_annotation_writer.py
sinapsis_data_writers/templates/audio_writers/__init__.py
sinapsis_data_writers/templates/audio_writers/audio_writer_soundfile.py
sinapsis_data_writers/templates/generic_data_writers/generic_data_json_writer.py
sinapsis_data_writers/templates/image_writers/__init__.py
sinapsis_data_writers/templates/image_writers/image_saver.py
sinapsis_data_writers/templates/image_writers/pdf_to_image_converter.py
sinapsis_data_writers/templates/video_writers/__init__.py
sinapsis_data_writers/templates/video_writers/base_video_writer.py
sinapsis_data_writers/templates/video_writers/video_writer_cv2.py
sinapsis_data_writers/templates/video_writers/video_writer_ffmpeg.py
sinapsis_data_writers-0.1.16.dist-info/licenses/LICENSE
sinapsis_data_writers-0.1.16.dist-info/METADATA
sinapsis_data_writers-0.1.16.dist-info/WHEEL
sinapsis_data_writers-0.1.16.dist-info/top_level.txt
sinapsis_data_writers-0.1.16.dist-info/RECORD
