Metadata-Version: 2.4
Name: sinapsis-data-writers
Version: 0.1.16
Summary: Templates to write DataContainer content to file.
Author-email: SinapsisAI <dev@sinapsis.tech>
Project-URL: Homepage, https://sinapsis.tech
Project-URL: Documentation, https://docs.sinapsis.tech/docs
Project-URL: Tutorials, https://docs.sinapsis.tech/tutorials
Project-URL: Repository, https://github.com/Sinapsis-AI/sinapsis-data-tools.git
Requires-Python: >=3.10
License-File: LICENSE
Requires-Dist: sinapsis>=0.1.1
Requires-Dist: sinapsis-generic-data-tools
Provides-Extra: pydub
Requires-Dist: pydub>=0.25.1; extra == "pydub"
Provides-Extra: soundfile
Requires-Dist: soundfile>=0.12.1; extra == "soundfile"
Provides-Extra: pdf-image-writer
Requires-Dist: pdf2image>=1.17.0; extra == "pdf-image-writer"
Provides-Extra: all
Requires-Dist: sinapsis-data-writers[ffmpeg,opencv,pdf-image-writer,pydub,soundfile]; extra == "all"
Provides-Extra: opencv
Requires-Dist: opencv-python-headless>=4.11.0.86; extra == "opencv"
Provides-Extra: ffmpeg
Requires-Dist: ffmpeg-python>=0.2.0; extra == "ffmpeg"
Dynamic: license-file
